[{"name":"天津市","code":"12","level":1,"mergeName":"天津市,天津市","lng":117.2095232146708,"lat":39.093667843403956,"info":"直接查询获得"},{"name":"市辖区","code":"1201","level":2,"mergeName":"天津市,市辖区","lng":117.2095232146708,"lat":39.093667843403956,"info":"直接查询获得"},{"name":"和平区","code":"120101","level":3,"mergeName":"天津市,市辖区,和平区","lng":117.22146699490091,"lat":39.12339025327971,"info":"直接查询获得"},{"name":"劝业场街道","code":"120101001","level":4,"mergeName":"天津市,市辖区,和平区,劝业场街道","lng":117.19875801126976,"lat":39.13282509535079,"info":"直接查询获得"},{"name":"小白楼街道","code":"120101002","level":4,"mergeName":"天津市,市辖区,和平区,小白楼街道","lng":117.21890915979179,"lat":39.12703692462491,"info":"直接查询获得"},{"name":"五大道街道","code":"120101003","level":4,"mergeName":"天津市,市辖区,和平区,五大道街道","lng":117.20085600378832,"lat":39.11141308199118,"info":"直接查询获得"},{"name":"新兴街道","code":"120101004","level":4,"mergeName":"天津市,市辖区,和平区,新兴街道","lng":117.19465580393806,"lat":39.111988764192695,"info":"直接查询获得"},{"name":"南营门街道","code":"120101005","level":4,"mergeName":"天津市,市辖区,和平区,南营门街道","lng":117.19810206858638,"lat":39.12165120369428,"info":"直接查询获得"},{"name":"南市街道","code":"120101006","level":4,"mergeName":"天津市,市辖区,和平区,南市街道","lng":117.19344377151687,"lat":39.13700679549578,"info":"直接查询获得"},{"name":"河东区","code":"120102","level":3,"mergeName":"天津市,市辖区,河东区","lng":117.25841295306803,"lat":39.134487325955114,"info":"直接查询获得"},{"name":"大王庄街道","code":"120102001","level":4,"mergeName":"天津市,市辖区,河东区,大王庄街道","lng":117.22852300502068,"lat":39.132805085094134,"info":"直接查询获得"},{"name":"大直沽街道","code":"120102002","level":4,"mergeName":"天津市,市辖区,河东区,大直沽街道","lng":117.25305006917345,"lat":39.116076394537615,"info":"直接查询获得"},{"name":"中山门街道","code":"120102003","level":4,"mergeName":"天津市,市辖区,河东区,中山门街道","lng":117.27719912636766,"lat":39.108251961181026,"info":"直接查询获得"},{"name":"富民路街道","code":"120102004","level":4,"mergeName":"天津市,市辖区,河东区,富民路街道","lng":117.25857204297385,"lat":39.09896311090355,"info":"直接查询获得"},{"name":"二号桥街道","code":"120102005","level":4,"mergeName":"天津市,市辖区,河东区,二号桥街道","lng":117.3152042765616,"lat":39.09438504227053,"info":"直接查询获得"},{"name":"春华街道","code":"120102006","level":4,"mergeName":"天津市,市辖区,河东区,春华街道","lng":117.21491735959711,"lat":39.146096229877905,"info":"直接查询获得"},{"name":"唐家口街道","code":"120102007","level":4,"mergeName":"天津市,市辖区,河东区,唐家口街道","lng":117.24794904133505,"lat":39.135078521427396,"info":"直接查询获得"},{"name":"向阳楼街道","code":"120102008","level":4,"mergeName":"天津市,市辖区,河东区,向阳楼街道","lng":117.2514507260435,"lat":39.140983205143854,"info":"直接查询获得"},{"name":"常州道街道","code":"120102009","level":4,"mergeName":"天津市,市辖区,河东区,常州道街道","lng":117.24554131307667,"lat":39.152687694658184,"info":"直接查询获得"},{"name":"上杭路街道","code":"120102010","level":4,"mergeName":"天津市,市辖区,河东区,上杭路街道","lng":117.25821658348356,"lat":39.135363762707584,"info":"直接查询获得"},{"name":"东新街道","code":"120102011","level":4,"mergeName":"天津市,市辖区,河东区,东新街道","lng":117.28379403626914,"lat":39.14157112759926,"info":"直接查询获得"},{"name":"鲁山道街道","code":"120102012","level":4,"mergeName":"天津市,市辖区,河东区,鲁山道街道","lng":117.28514251950071,"lat":39.160085822927066,"info":"直接查询获得"},{"name":"天津铁厂街道","code":"120102013","level":4,"mergeName":"天津市,市辖区,河东区,天津铁厂街道","lng":113.74809261906054,"lat":36.62401318018441,"info":"直接查询获得"},{"name":"河西区","code":"120103","level":3,"mergeName":"天津市,市辖区,河西区","lng":117.2294162800198,"lat":39.115718082215515,"info":"直接查询获得"},{"name":"大营门街道","code":"120103001","level":4,"mergeName":"天津市,市辖区,河西区,大营门街道","lng":117.2209482234689,"lat":39.11493545733194,"info":"直接查询获得"},{"name":"下瓦房街道","code":"120103002","level":4,"mergeName":"天津市,市辖区,河西区,下瓦房街道","lng":117.23166339125301,"lat":39.112418933167355,"info":"直接查询获得"},{"name":"桃园街道","code":"120103003","level":4,"mergeName":"天津市,市辖区,河西区,桃园街道","lng":117.22003895863169,"lat":39.1078980881653,"info":"直接查询获得"},{"name":"挂甲寺街道","code":"120103004","level":4,"mergeName":"天津市,市辖区,河西区,挂甲寺街道","lng":117.23334519882879,"lat":39.10541028790888,"info":"直接查询获得"},{"name":"马场街道","code":"120103005","level":4,"mergeName":"天津市,市辖区,河西区,马场街道","lng":117.19537687916076,"lat":39.10115806108476,"info":"直接查询获得"},{"name":"越秀路街道","code":"120103006","level":4,"mergeName":"天津市,市辖区,河西区,越秀路街道","lng":117.22051497072142,"lat":39.10291609950015,"info":"直接查询获得"},{"name":"友谊路街道","code":"120103007","level":4,"mergeName":"天津市,市辖区,河西区,友谊路街道","lng":117.2080874529742,"lat":39.091091397203265,"info":"直接查询获得"},{"name":"天塔街道","code":"120103008","level":4,"mergeName":"天津市,市辖区,河西区,天塔街道","lng":117.2080874529742,"lat":39.091091397203265,"info":"直接查询获得"},{"name":"尖山街道","code":"120103009","level":4,"mergeName":"天津市,市辖区,河西区,尖山街道","lng":117.23667370191288,"lat":39.078087414373314,"info":"直接查询获得"},{"name":"陈塘庄街道","code":"120103010","level":4,"mergeName":"天津市,市辖区,河西区,陈塘庄街道","lng":117.26375733186909,"lat":39.07868171060735,"info":"直接查询获得"},{"name":"柳林街道","code":"120103011","level":4,"mergeName":"天津市,市辖区,河西区,柳林街道","lng":117.28357717543769,"lat":39.07619234557941,"info":"直接查询获得"},{"name":"东海街道","code":"120103012","level":4,"mergeName":"天津市,市辖区,河西区,东海街道","lng":117.26256896350995,"lat":39.060044073558004,"info":"直接查询获得"},{"name":"梅江街道","code":"120103013","level":4,"mergeName":"天津市,市辖区,河西区,梅江街道","lng":117.22066031655294,"lat":39.070095456267744,"info":"直接查询获得"},{"name":"太湖路街道","code":"120103014","level":4,"mergeName":"天津市,市辖区,河西区,太湖路街道","lng":117.2294162800198,"lat":39.115718082215515,"info":"直接查询获得"},{"name":"南开区","code":"120104","level":3,"mergeName":"天津市,市辖区,南开区","lng":117.15651537432414,"lat":39.14410527976771,"info":"直接查询获得"},{"name":"长虹街道","code":"120104001","level":4,"mergeName":"天津市,市辖区,南开区,长虹街道","lng":117.15416851075558,"lat":39.14368214774101,"info":"直接查询获得"},{"name":"鼓楼街道","code":"120104002","level":4,"mergeName":"天津市,市辖区,南开区,鼓楼街道","lng":117.19050367597256,"lat":39.147010285710365,"info":"直接查询获得"},{"name":"兴南街道","code":"120104003","level":4,"mergeName":"天津市,市辖区,南开区,兴南街道","lng":117.18227708124782,"lat":39.13548531893612,"info":"直接查询获得"},{"name":"广开街道","code":"120104004","level":4,"mergeName":"天津市,市辖区,南开区,广开街道","lng":117.17133583152618,"lat":39.140289623426916,"info":"直接查询获得"},{"name":"万兴街道","code":"120104005","level":4,"mergeName":"天津市,市辖区,南开区,万兴街道","lng":117.16964094192726,"lat":39.1267537405241,"info":"直接查询获得"},{"name":"学府街道","code":"120104006","level":4,"mergeName":"天津市,市辖区,南开区,学府街道","lng":117.1704817558846,"lat":39.1129302055791,"info":"直接查询获得"},{"name":"向阳路街道","code":"120104007","level":4,"mergeName":"天津市,市辖区,南开区,向阳路街道","lng":117.13387887586292,"lat":39.14494424855367,"info":"直接查询获得"},{"name":"嘉陵道街道","code":"120104008","level":4,"mergeName":"天津市,市辖区,南开区,嘉陵道街道","lng":117.1423219199952,"lat":39.12986526031182,"info":"直接查询获得"},{"name":"王顶堤街道","code":"120104009","level":4,"mergeName":"天津市,市辖区,南开区,王顶堤街道","lng":117.14784534905053,"lat":39.10954375284136,"info":"直接查询获得"},{"name":"水上公园街道","code":"120104010","level":4,"mergeName":"天津市,市辖区,南开区,水上公园街道","lng":117.16998374159799,"lat":39.095978227351225,"info":"直接查询获得"},{"name":"体育中心街道","code":"120104011","level":4,"mergeName":"天津市,市辖区,南开区,体育中心街道","lng":117.17695721989904,"lat":39.078925381408624,"info":"直接查询获得"},{"name":"华苑街道","code":"120104012","level":4,"mergeName":"天津市,市辖区,南开区,华苑街道","lng":117.15157887024158,"lat":39.091891620554264,"info":"直接查询获得"},{"name":"河北区","code":"120105","level":3,"mergeName":"天津市,市辖区,河北区","lng":117.20359278135501,"lat":39.15348514470478,"info":"直接查询获得"},{"name":"光复道街道","code":"120105001","level":4,"mergeName":"天津市,市辖区,河北区,光复道街道","lng":117.20894102286977,"lat":39.15099309180212,"info":"直接查询获得"},{"name":"望海楼街道","code":"120105002","level":4,"mergeName":"天津市,市辖区,河北区,望海楼街道","lng":117.21442948987463,"lat":39.16700445663188,"info":"直接查询获得"},{"name":"鸿顺里街道","code":"120105003","level":4,"mergeName":"天津市,市辖区,河北区,鸿顺里街道","lng":117.20202937044544,"lat":39.16413090498557,"info":"直接查询获得"},{"name":"新开河街道","code":"120105004","level":4,"mergeName":"天津市,市辖区,河北区,新开河街道","lng":117.19089083127449,"lat":39.18113691543051,"info":"直接查询获得"},{"name":"铁东路街道","code":"120105005","level":4,"mergeName":"天津市,市辖区,河北区,铁东路街道","lng":117.21037867100794,"lat":39.19483597455412,"info":"直接查询获得"},{"name":"建昌道街道","code":"120105006","level":4,"mergeName":"天津市,市辖区,河北区,建昌道街道","lng":117.23801463398831,"lat":39.184171748888545,"info":"直接查询获得"},{"name":"宁园街道","code":"120105007","level":4,"mergeName":"天津市,市辖区,河北区,宁园街道","lng":117.22510315594418,"lat":39.1676249576126,"info":"直接查询获得"},{"name":"王串场街道","code":"120105008","level":4,"mergeName":"天津市,市辖区,河北区,王串场街道","lng":117.22638503790694,"lat":39.16054813573881,"info":"直接查询获得"},{"name":"江都路街道","code":"120105009","level":4,"mergeName":"天津市,市辖区,河北区,江都路街道","lng":117.24232897257298,"lat":39.16946712698328,"info":"直接查询获得"},{"name":"月牙河街道","code":"120105010","level":4,"mergeName":"天津市,市辖区,河北区,月牙河街道","lng":117.26219023790694,"lat":39.166736687739665,"info":"直接查询获得"},{"name":"红桥区","code":"120106","level":3,"mergeName":"天津市,市辖区,红桥区","lng":117.15751788327329,"lat":39.17328564656417,"info":"直接查询获得"},{"name":"西于庄街道","code":"120106001","level":4,"mergeName":"天津市,市辖区,红桥区,西于庄街道","lng":117.17097701506819,"lat":39.17227109189047,"info":"直接查询获得"},{"name":"双环村街道","code":"120106002","level":4,"mergeName":"天津市,市辖区,红桥区,双环村街道","lng":117.13737661611187,"lat":39.20656574822994,"info":"直接查询获得"},{"name":"咸阳北路街道","code":"120106003","level":4,"mergeName":"天津市,市辖区,红桥区,咸阳北路街道","lng":117.15319505749817,"lat":39.190978577929805,"info":"直接查询获得"},{"name":"丁字沽街道","code":"120106004","level":4,"mergeName":"天津市,市辖区,红桥区,丁字沽街道","lng":117.17102597271847,"lat":39.180261752524956,"info":"直接查询获得"},{"name":"西沽街道","code":"120106005","level":4,"mergeName":"天津市,市辖区,红桥区,西沽街道","lng":117.142227016713,"lat":39.17143008207838,"info":"直接查询获得"},{"name":"三条石街道","code":"120106006","level":4,"mergeName":"天津市,市辖区,红桥区,三条石街道","lng":117.17776353353497,"lat":39.16020292020142,"info":"直接查询获得"},{"name":"邵公庄街道","code":"120106008","level":4,"mergeName":"天津市,市辖区,红桥区,邵公庄街道","lng":117.14153999265896,"lat":39.15951311345588,"info":"直接查询获得"},{"name":"芥园街道","code":"120106009","level":4,"mergeName":"天津市,市辖区,红桥区,芥园街道","lng":117.15751788327329,"lat":39.17328564656417,"info":"直接查询获得"},{"name":"铃铛阁街道","code":"120106010","level":4,"mergeName":"天津市,市辖区,红桥区,铃铛阁街道","lng":117.16497723256704,"lat":39.150257377800195,"info":"直接查询获得"},{"name":"和苑街道","code":"120106012","level":4,"mergeName":"天津市,市辖区,红桥区,和苑街道","lng":117.15751788327329,"lat":39.17328564656417,"info":"直接查询获得"},{"name":"东丽区","code":"120110","level":3,"mergeName":"天津市,市辖区,东丽区","lng":117.32056850791443,"lat":39.09233234281453,"info":"直接查询获得"},{"name":"张贵庄街道","code":"120110001","level":4,"mergeName":"天津市,市辖区,东丽区,张贵庄街道","lng":117.3212112419136,"lat":39.096174371257376,"info":"直接查询获得"},{"name":"丰年村街道","code":"120110002","level":4,"mergeName":"天津市,市辖区,东丽区,丰年村街道","lng":117.34270815808962,"lat":39.09817773844565,"info":"直接查询获得"},{"name":"万新街道","code":"120110003","level":4,"mergeName":"天津市,市辖区,东丽区,万新街道","lng":117.30909195614278,"lat":39.12644718788633,"info":"直接查询获得"},{"name":"无瑕街道","code":"120110004","level":4,"mergeName":"天津市,市辖区,东丽区,无瑕街道","lng":117.50610103353684,"lat":39.034793800240614,"info":"直接查询获得"},{"name":"新立街道","code":"120110005","level":4,"mergeName":"天津市,市辖区,东丽区,新立街道","lng":117.38600448943234,"lat":39.07907845051328,"info":"直接查询获得"},{"name":"华明街道","code":"120110006","level":4,"mergeName":"天津市,市辖区,东丽区,华明街道","lng":117.37535157871157,"lat":39.18325643113116,"info":"直接查询获得"},{"name":"金钟街道","code":"120110007","level":4,"mergeName":"天津市,市辖区,东丽区,金钟街道","lng":117.30481744123799,"lat":39.213675920932936,"info":"直接查询获得"},{"name":"军粮城街道","code":"120110008","level":4,"mergeName":"天津市,市辖区,东丽区,军粮城街道","lng":117.4877682997061,"lat":39.10301693135056,"info":"直接查询获得"},{"name":"金桥街道","code":"120110009","level":4,"mergeName":"天津市,市辖区,东丽区,金桥街道","lng":117.39812856406982,"lat":39.11775570439963,"info":"直接查询获得"},{"name":"华新街道","code":"120110010","level":4,"mergeName":"天津市,市辖区,东丽区,华新街道","lng":117.42902622674674,"lat":39.175095804244876,"info":"直接查询获得"},{"name":"东丽湖街道","code":"120110011","level":4,"mergeName":"天津市,市辖区,东丽区,东丽湖街道","lng":117.49210299928346,"lat":39.19334270028226,"info":"直接查询获得"},{"name":"天津经济技术开发区西区","code":"120110400","level":4,"mergeName":"天津市,市辖区,东丽区,天津经济技术开发区西区","lng":117.32056850791443,"lat":39.09233234281453,"info":"直接查询获得"},{"name":"天津航空物流区","code":"120110401","level":4,"mergeName":"天津市,市辖区,东丽区,天津航空物流区","lng":117.33910908448762,"lat":39.139116147754294,"info":"直接查询获得"},{"name":"天津空港经济区","code":"120110402","level":4,"mergeName":"天津市,市辖区,东丽区,天津空港经济区","lng":117.34121444311134,"lat":39.16438406761165,"info":"直接查询获得"},{"name":"东丽区经济技术开发区","code":"120110403","level":4,"mergeName":"天津市,市辖区,东丽区,东丽区经济技术开发区","lng":117.32056850791443,"lat":39.09233234281453,"info":"直接查询获得"},{"name":"综合保税区","code":"120110405","level":4,"mergeName":"天津市,市辖区,东丽区,综合保税区","lng":117.4000609997812,"lat":39.16474213030996,"info":"直接查询获得"},{"name":"航空新城","code":"120110406","level":4,"mergeName":"天津市,市辖区,东丽区,航空新城","lng":117.32056850791443,"lat":39.09233234281453,"info":"直接查询获得"},{"name":"服务滨海新区建设管理委员会","code":"120110407","level":4,"mergeName":"天津市,市辖区,东丽区,服务滨海新区建设管理委员会","lng":117.3408090378347,"lat":39.12229946866721,"info":"直接查询获得"},{"name":"西青区","code":"120111","level":3,"mergeName":"天津市,市辖区,西青区","lng":117.01441017993696,"lat":39.14872660896657,"info":"直接查询获得"},{"name":"西营门街道","code":"120111001","level":4,"mergeName":"天津市,市辖区,西青区,西营门街道","lng":117.10132896345472,"lat":39.15806507760238,"info":"直接查询获得"},{"name":"李七庄街道","code":"120111002","level":4,"mergeName":"天津市,市辖区,西青区,李七庄街道","lng":117.1513871278288,"lat":39.07370765427488,"info":"直接查询获得"},{"name":"赤龙南街道","code":"120111003","level":4,"mergeName":"天津市,市辖区,西青区,赤龙南街道","lng":117.26965300076162,"lat":38.99975069414688,"info":"直接查询获得"},{"name":"中北镇","code":"120111100","level":4,"mergeName":"天津市,市辖区,西青区,中北镇","lng":117.08904014407823,"lat":39.13079528448552,"info":"直接查询获得"},{"name":"杨柳青镇","code":"120111101","level":4,"mergeName":"天津市,市辖区,西青区,杨柳青镇","lng":117.02164486302267,"lat":39.13463977790544,"info":"直接查询获得"},{"name":"辛口镇","code":"120111102","level":4,"mergeName":"天津市,市辖区,西青区,辛口镇","lng":116.97712600974532,"lat":39.096274435800915,"info":"直接查询获得"},{"name":"张家窝镇","code":"120111103","level":4,"mergeName":"天津市,市辖区,西青区,张家窝镇","lng":117.05512058436065,"lat":39.070354588434476,"info":"直接查询获得"},{"name":"精武镇","code":"120111104","level":4,"mergeName":"天津市,市辖区,西青区,精武镇","lng":117.12112671858912,"lat":39.04989654189401,"info":"直接查询获得"},{"name":"大寺镇","code":"120111105","level":4,"mergeName":"天津市,市辖区,西青区,大寺镇","lng":117.24653492880125,"lat":39.02640583373706,"info":"直接查询获得"},{"name":"王稳庄镇","code":"120111106","level":4,"mergeName":"天津市,市辖区,西青区,王稳庄镇","lng":117.27274460900477,"lat":38.90021586913139,"info":"直接查询获得"},{"name":"天津经济技术开发区微电子小区","code":"120111400","level":4,"mergeName":"天津市,市辖区,西青区,天津经济技术开发区微电子小区","lng":117.25793828843656,"lat":39.00994887141812,"info":"直接查询获得"},{"name":"新技术产业园区","code":"120111401","level":4,"mergeName":"天津市,市辖区,西青区,新技术产业园区","lng":117.13115899452455,"lat":39.10301311371113,"info":"直接查询获得"},{"name":"西青区开发区","code":"120111450","level":4,"mergeName":"天津市,市辖区,西青区,西青区开发区","lng":117.01441017993696,"lat":39.14872660896657,"info":"直接查询获得"},{"name":"津南区","code":"120112","level":3,"mergeName":"天津市,市辖区,津南区","lng":117.36338677903083,"lat":38.94414856811469,"info":"直接查询获得"},{"name":"双新街道","code":"120112001","level":4,"mergeName":"天津市,市辖区,津南区,双新街道","lng":117.36338677903083,"lat":38.94414856811469,"info":"直接查询获得"},{"name":"双林街道","code":"120112002","level":4,"mergeName":"天津市,市辖区,津南区,双林街道","lng":117.36338677903083,"lat":38.94414856811469,"info":"直接查询获得"},{"name":"咸水沽镇","code":"120112100","level":4,"mergeName":"天津市,市辖区,津南区,咸水沽镇","lng":117.39004733943085,"lat":39.00355943693909,"info":"直接查询获得"},{"name":"葛沽镇","code":"120112101","level":4,"mergeName":"天津市,市辖区,津南区,葛沽镇","lng":117.49737030347175,"lat":38.9982323327025,"info":"直接查询获得"},{"name":"小站镇","code":"120112102","level":4,"mergeName":"天津市,市辖区,津南区,小站镇","lng":117.45095234251578,"lat":38.93064589106057,"info":"直接查询获得"},{"name":"双港镇","code":"120112103","level":4,"mergeName":"天津市,市辖区,津南区,双港镇","lng":117.32506165241423,"lat":39.048095491051114,"info":"直接查询获得"},{"name":"辛庄镇","code":"120112104","level":4,"mergeName":"天津市,市辖区,津南区,辛庄镇","lng":117.3566181368437,"lat":39.03263310150959,"info":"直接查询获得"},{"name":"双桥河镇","code":"120112106","level":4,"mergeName":"天津市,市辖区,津南区,双桥河镇","lng":117.45303670863804,"lat":39.0004905436741,"info":"直接查询获得"},{"name":"八里台镇","code":"120112107","level":4,"mergeName":"天津市,市辖区,津南区,八里台镇","lng":117.34991605909485,"lat":38.95328497152021,"info":"直接查询获得"},{"name":"北闸口镇","code":"120112108","level":4,"mergeName":"天津市,市辖区,津南区,北闸口镇","lng":117.41255175823633,"lat":38.95631988792704,"info":"直接查询获得"},{"name":"铁路十八局","code":"120112401","level":4,"mergeName":"天津市,市辖区,津南区,铁路十八局","lng":117.36338677903083,"lat":38.94414856811469,"info":"直接查询获得"},{"name":"长青","code":"120112403","level":4,"mergeName":"天津市,市辖区,津南区,长青","lng":117.36338677903083,"lat":38.94414856811469,"info":"直接查询获得"},{"name":"津南开发区东区","code":"120112404","level":4,"mergeName":"天津市,市辖区,津南区,津南开发区东区","lng":117.45946423637557,"lat":38.98710011387774,"info":"直接查询获得"},{"name":"津南开发区西区","code":"120112405","level":4,"mergeName":"天津市,市辖区,津南区,津南开发区西区","lng":117.30899869226812,"lat":39.038408418403044,"info":"直接查询获得"},{"name":"海河教育园区","code":"120112407","level":4,"mergeName":"天津市,市辖区,津南区,海河教育园区","lng":117.38418416853673,"lat":39.023588866697715,"info":"直接查询获得"},{"name":"津南国家农业园区","code":"120112501","level":4,"mergeName":"天津市,市辖区,津南区,津南国家农业园区","lng":117.35849200213752,"lat":38.94419711503746,"info":"直接查询获得"},{"name":"北辰区","code":"120113","level":3,"mergeName":"天津市,市辖区,北辰区","lng":117.14140273157703,"lat":39.2303439099184,"info":"直接查询获得"},{"name":"果园新村街道","code":"120113001","level":4,"mergeName":"天津市,市辖区,北辰区,果园新村街道","lng":117.14248995073577,"lat":39.23084528188834,"info":"直接查询获得"},{"name":"集贤里街道","code":"120113002","level":4,"mergeName":"天津市,市辖区,北辰区,集贤里街道","lng":117.13872218793526,"lat":39.236925247453904,"info":"直接查询获得"},{"name":"普东街道","code":"120113003","level":4,"mergeName":"天津市,市辖区,北辰区,普东街道","lng":117.21611030931435,"lat":39.213353538357424,"info":"直接查询获得"},{"name":"瑞景街道","code":"120113004","level":4,"mergeName":"天津市,市辖区,北辰区,瑞景街道","lng":117.11270779934961,"lat":39.20143241098485,"info":"直接查询获得"},{"name":"佳荣里街道","code":"120113005","level":4,"mergeName":"天津市,市辖区,北辰区,佳荣里街道","lng":117.12828998638679,"lat":39.2006671028773,"info":"直接查询获得"},{"name":"青源街道","code":"120113006","level":4,"mergeName":"天津市,市辖区,北辰区,青源街道","lng":117.08276061127515,"lat":39.217814788007466,"info":"直接查询获得"},{"name":"广源街道","code":"120113007","level":4,"mergeName":"天津市,市辖区,北辰区,广源街道","lng":117.09225473034567,"lat":39.217691666255575,"info":"直接查询获得"},{"name":"天穆镇","code":"120113100","level":4,"mergeName":"天津市,市辖区,北辰区,天穆镇","lng":117.15617087416108,"lat":39.20774006373754,"info":"直接查询获得"},{"name":"北仓镇","code":"120113101","level":4,"mergeName":"天津市,市辖区,北辰区,北仓镇","lng":117.13185122875055,"lat":39.238140548089056,"info":"直接查询获得"},{"name":"双街镇","code":"120113102","level":4,"mergeName":"天津市,市辖区,北辰区,双街镇","lng":117.13821257921946,"lat":39.26846749449635,"info":"直接查询获得"},{"name":"双口镇","code":"120113103","level":4,"mergeName":"天津市,市辖区,北辰区,双口镇","lng":117.01767094629407,"lat":39.226928228033316,"info":"直接查询获得"},{"name":"青光镇","code":"120113104","level":4,"mergeName":"天津市,市辖区,北辰区,青光镇","lng":117.04473302140957,"lat":39.22133012668062,"info":"直接查询获得"},{"name":"宜兴埠镇","code":"120113106","level":4,"mergeName":"天津市,市辖区,北辰区,宜兴埠镇","lng":117.23803606037134,"lat":39.2196814946926,"info":"直接查询获得"},{"name":"小淀镇","code":"120113107","level":4,"mergeName":"天津市,市辖区,北辰区,小淀镇","lng":117.22743749264242,"lat":39.25551515355714,"info":"直接查询获得"},{"name":"大张庄镇","code":"120113108","level":4,"mergeName":"天津市,市辖区,北辰区,大张庄镇","lng":117.217424620106,"lat":39.32465982359833,"info":"直接查询获得"},{"name":"西堤头镇","code":"120113111","level":4,"mergeName":"天津市,市辖区,北辰区,西堤头镇","lng":117.35981763157858,"lat":39.26071727489328,"info":"直接查询获得"},{"name":"科技园区北区","code":"120113400","level":4,"mergeName":"天津市,市辖区,北辰区,科技园区北区","lng":117.28825861465374,"lat":39.237777972114536,"info":"直接查询获得"},{"name":"科技园区南区","code":"120113401","level":4,"mergeName":"天津市,市辖区,北辰区,科技园区南区","lng":117.27642074464326,"lat":39.23672844723414,"info":"直接查询获得"},{"name":"天津医药医疗器械工业园","code":"120113402","level":4,"mergeName":"天津市,市辖区,北辰区,天津医药医疗器械工业园","lng":117.03564055269868,"lat":39.238515207944815,"info":"直接查询获得"},{"name":"天津陆路港物流装备产业园","code":"120113403","level":4,"mergeName":"天津市,市辖区,北辰区,天津陆路港物流装备产业园","lng":117.32437804192115,"lat":39.254461076995796,"info":"直接查询获得"},{"name":"天津风电产业园","code":"120113404","level":4,"mergeName":"天津市,市辖区,北辰区,天津风电产业园","lng":117.1843125400249,"lat":39.305173290338935,"info":"直接查询获得"},{"name":"红旗农场","code":"120113500","level":4,"mergeName":"天津市,市辖区,北辰区,红旗农场","lng":117.21419646942535,"lat":39.2250912345604,"info":"直接查询获得"},{"name":"曙光农场","code":"120113501","level":4,"mergeName":"天津市,市辖区,北辰区,曙光农场","lng":117.14140273157703,"lat":39.2303439099184,"info":"直接查询获得"},{"name":"武清区","code":"120114","level":3,"mergeName":"天津市,市辖区,武清区","lng":117.05059715977872,"lat":39.389871228788344,"info":"直接查询获得"},{"name":"杨村街道","code":"120114001","level":4,"mergeName":"天津市,市辖区,武清区,杨村街道","lng":117.06902787358803,"lat":39.39874020489817,"info":"直接查询获得"},{"name":"下朱庄街道","code":"120114002","level":4,"mergeName":"天津市,市辖区,武清区,下朱庄街道","lng":117.10816042414616,"lat":39.33743243464044,"info":"直接查询获得"},{"name":"东蒲洼街道","code":"120114003","level":4,"mergeName":"天津市,市辖区,武清区,东蒲洼街道","lng":117.0124819671598,"lat":39.400587129207636,"info":"直接查询获得"},{"name":"黄庄街道","code":"120114004","level":4,"mergeName":"天津市,市辖区,武清区,黄庄街道","lng":117.03437119131814,"lat":39.34453295269044,"info":"直接查询获得"},{"name":"徐官屯街道","code":"120114005","level":4,"mergeName":"天津市,市辖区,武清区,徐官屯街道","lng":117.09200796582208,"lat":39.403868105353986,"info":"直接查询获得"},{"name":"运河西街道","code":"120114006","level":4,"mergeName":"天津市,市辖区,武清区,运河西街道","lng":117.05113784986517,"lat":39.38988147582684,"info":"直接查询获得"},{"name":"梅厂镇","code":"120114101","level":4,"mergeName":"天津市,市辖区,武清区,梅厂镇","lng":117.17899249991333,"lat":39.37564969468827,"info":"直接查询获得"},{"name":"大碱厂镇","code":"120114102","level":4,"mergeName":"天津市,市辖区,武清区,大碱厂镇","lng":117.09802104324477,"lat":39.4784200960278,"info":"直接查询获得"},{"name":"崔黄口镇","code":"120114103","level":4,"mergeName":"天津市,市辖区,武清区,崔黄口镇","lng":117.20442649869882,"lat":39.53959122684325,"info":"直接查询获得"},{"name":"大良镇","code":"120114104","level":4,"mergeName":"天津市,市辖区,武清区,大良镇","lng":117.15135505832208,"lat":39.553986365451095,"info":"直接查询获得"},{"name":"下伍旗镇","code":"120114105","level":4,"mergeName":"天津市,市辖区,武清区,下伍旗镇","lng":117.0474066606752,"lat":39.625028990172474,"info":"直接查询获得"},{"name":"南蔡村镇","code":"120114106","level":4,"mergeName":"天津市,市辖区,武清区,南蔡村镇","lng":117.02540723599012,"lat":39.49337517224572,"info":"直接查询获得"},{"name":"大孟庄镇","code":"120114107","level":4,"mergeName":"天津市,市辖区,武清区,大孟庄镇","lng":116.99867653859081,"lat":39.52796898548922,"info":"直接查询获得"},{"name":"泗村店镇","code":"120114108","level":4,"mergeName":"天津市,市辖区,武清区,泗村店镇","lng":116.94874079888486,"lat":39.47927839297254,"info":"直接查询获得"},{"name":"河西务镇","code":"120114109","level":4,"mergeName":"天津市,市辖区,武清区,河西务镇","lng":116.94252821499484,"lat":39.643153479549504,"info":"直接查询获得"},{"name":"城关镇","code":"120114110","level":4,"mergeName":"天津市,市辖区,武清区,城关镇","lng":116.87958925509963,"lat":39.538620208012176,"info":"直接查询获得"},{"name":"东马圈镇","code":"120114111","level":4,"mergeName":"天津市,市辖区,武清区,东马圈镇","lng":116.84275702241007,"lat":39.454082681235626,"info":"直接查询获得"},{"name":"黄花店镇","code":"120114112","level":4,"mergeName":"天津市,市辖区,武清区,黄花店镇","lng":116.91462119371667,"lat":39.35843175255947,"info":"直接查询获得"},{"name":"石各庄镇","code":"120114113","level":4,"mergeName":"天津市,市辖区,武清区,石各庄镇","lng":116.9120735094598,"lat":39.305489730957255,"info":"直接查询获得"},{"name":"王庆坨镇","code":"120114114","level":4,"mergeName":"天津市,市辖区,武清区,王庆坨镇","lng":116.9101452239199,"lat":39.191432089590656,"info":"直接查询获得"},{"name":"汊沽港镇","code":"120114115","level":4,"mergeName":"天津市,市辖区,武清区,汊沽港镇","lng":116.93804134875225,"lat":39.250896176388366,"info":"直接查询获得"},{"name":"河北屯镇","code":"120114116","level":4,"mergeName":"天津市,市辖区,武清区,河北屯镇","lng":117.13553814405515,"lat":39.586025264688026,"info":"直接查询获得"},{"name":"上马台镇","code":"120114117","level":4,"mergeName":"天津市,市辖区,武清区,上马台镇","lng":117.2682934198638,"lat":39.393061616933934,"info":"直接查询获得"},{"name":"大王古庄镇","code":"120114118","level":4,"mergeName":"天津市,市辖区,武清区,大王古庄镇","lng":116.83801838987881,"lat":39.57937020976965,"info":"直接查询获得"},{"name":"陈咀镇","code":"120114119","level":4,"mergeName":"天津市,市辖区,武清区,陈咀镇","lng":116.99719196297279,"lat":39.30712957041672,"info":"直接查询获得"},{"name":"豆张庄镇","code":"120114120","level":4,"mergeName":"天津市,市辖区,武清区,豆张庄镇","lng":116.95431461928605,"lat":39.40526628526686,"info":"直接查询获得"},{"name":"曹子里镇","code":"120114121","level":4,"mergeName":"天津市,市辖区,武清区,曹子里镇","lng":117.14307196287568,"lat":39.422211132841355,"info":"直接查询获得"},{"name":"大黄堡镇","code":"120114122","level":4,"mergeName":"天津市,市辖区,武清区,大黄堡镇","lng":117.26434895587796,"lat":39.45747706921244,"info":"直接查询获得"},{"name":"高村镇","code":"120114123","level":4,"mergeName":"天津市,市辖区,武清区,高村镇","lng":116.88823571512484,"lat":39.64489005884489,"info":"直接查询获得"},{"name":"白古屯镇","code":"120114124","level":4,"mergeName":"天津市,市辖区,武清区,白古屯镇","lng":116.91387524082117,"lat":39.55627440447086,"info":"直接查询获得"},{"name":"天津经济技术开发区逸仙科学工业园","code":"120114400","level":4,"mergeName":"天津市,市辖区,武清区,天津经济技术开发区逸仙科学工业园","lng":117.03785837917228,"lat":39.41030561750854,"info":"直接查询获得"},{"name":"武清经济技术开发区","code":"120114401","level":4,"mergeName":"天津市,市辖区,武清区,武清经济技术开发区","lng":117.05059715977872,"lat":39.389871228788344,"info":"直接查询获得"},{"name":"天津京滨工业园","code":"120114403","level":4,"mergeName":"天津市,市辖区,武清区,天津京滨工业园","lng":116.83237602427566,"lat":39.56586328507697,"info":"直接查询获得"},{"name":"天津京津电子商务产业园","code":"120114404","level":4,"mergeName":"天津市,市辖区,武清区,天津京津电子商务产业园","lng":117.1947639653113,"lat":39.52455211480028,"info":"直接查询获得"},{"name":"天津武清汽车产业园","code":"120114405","level":4,"mergeName":"天津市,市辖区,武清区,天津武清汽车产业园","lng":117.20855520065324,"lat":39.38826751371449,"info":"直接查询获得"},{"name":"天津京津科技谷","code":"120114406","level":4,"mergeName":"天津市,市辖区,武清区,天津京津科技谷","lng":116.94031803130454,"lat":39.26111709425613,"info":"直接查询获得"},{"name":"京津高村科技创新园","code":"120114407","level":4,"mergeName":"天津市,市辖区,武清区,京津高村科技创新园","lng":116.84461103515213,"lat":39.63425508346666,"info":"直接查询获得"},{"name":"武清农场","code":"120114500","level":4,"mergeName":"天津市,市辖区,武清区,武清农场","lng":117.05059715977872,"lat":39.389871228788344,"info":"直接查询获得"},{"name":"宝坻区","code":"120115","level":3,"mergeName":"天津市,市辖区,宝坻区","lng":117.31660069247685,"lat":39.723194482933174,"info":"直接查询获得"},{"name":"海滨街道","code":"120115001","level":4,"mergeName":"天津市,市辖区,宝坻区,海滨街道","lng":117.32066410918002,"lat":39.73926760808254,"info":"直接查询获得"},{"name":"宝平街道","code":"120115002","level":4,"mergeName":"天津市,市辖区,宝坻区,宝平街道","lng":117.3164390873156,"lat":39.723046653396004,"info":"直接查询获得"},{"name":"钰华街道","code":"120115003","level":4,"mergeName":"天津市,市辖区,宝坻区,钰华街道","lng":117.32836382346892,"lat":39.71853745623604,"info":"直接查询获得"},{"name":"周良街道","code":"120115006","level":4,"mergeName":"天津市,市辖区,宝坻区,周良街道","lng":117.38730155814802,"lat":39.569586038977405,"info":"直接查询获得"},{"name":"潮阳街道","code":"120115007","level":4,"mergeName":"天津市,市辖区,宝坻区,潮阳街道","lng":117.26932537796247,"lat":39.658045837790915,"info":"直接查询获得"},{"name":"朝霞街道","code":"120115008","level":4,"mergeName":"天津市,市辖区,宝坻区,朝霞街道","lng":117.35778710180384,"lat":39.751741167930774,"info":"直接查询获得"},{"name":"大口屯镇","code":"120115101","level":4,"mergeName":"天津市,市辖区,宝坻区,大口屯镇","lng":117.24455856684875,"lat":39.59162578866355,"info":"直接查询获得"},{"name":"王卜庄镇","code":"120115103","level":4,"mergeName":"天津市,市辖区,宝坻区,王卜庄镇","lng":117.48968925237814,"lat":39.71128170008825,"info":"直接查询获得"},{"name":"方家庄镇","code":"120115104","level":4,"mergeName":"天津市,市辖区,宝坻区,方家庄镇","lng":117.43615536432486,"lat":39.736053181288014,"info":"直接查询获得"},{"name":"林亭口镇","code":"120115105","level":4,"mergeName":"天津市,市辖区,宝坻区,林亭口镇","lng":117.52202187276824,"lat":39.64094468567624,"info":"直接查询获得"},{"name":"八门城镇","code":"120115106","level":4,"mergeName":"天津市,市辖区,宝坻区,八门城镇","lng":117.61976254276468,"lat":39.585783370157806,"info":"直接查询获得"},{"name":"大钟庄镇","code":"120115107","level":4,"mergeName":"天津市,市辖区,宝坻区,大钟庄镇","lng":117.57804038403155,"lat":39.69616508878736,"info":"直接查询获得"},{"name":"新安镇","code":"120115108","level":4,"mergeName":"天津市,市辖区,宝坻区,新安镇","lng":117.54658235388598,"lat":39.76155955822116,"info":"直接查询获得"},{"name":"霍各庄镇","code":"120115111","level":4,"mergeName":"天津市,市辖区,宝坻区,霍各庄镇","lng":117.36125402208904,"lat":39.77688450368513,"info":"直接查询获得"},{"name":"新开口镇","code":"120115113","level":4,"mergeName":"天津市,市辖区,宝坻区,新开口镇","lng":117.20398944072922,"lat":39.688714162004814,"info":"直接查询获得"},{"name":"大唐庄镇","code":"120115115","level":4,"mergeName":"天津市,市辖区,宝坻区,大唐庄镇","lng":117.46720079017342,"lat":39.416757946021015,"info":"直接查询获得"},{"name":"牛道口镇","code":"120115119","level":4,"mergeName":"天津市,市辖区,宝坻区,牛道口镇","lng":117.26810737630116,"lat":39.79951353331972,"info":"直接查询获得"},{"name":"史各庄镇","code":"120115120","level":4,"mergeName":"天津市,市辖区,宝坻区,史各庄镇","lng":117.21380441386687,"lat":39.73954044108512,"info":"直接查询获得"},{"name":"郝各庄镇","code":"120115121","level":4,"mergeName":"天津市,市辖区,宝坻区,郝各庄镇","lng":117.33997679461024,"lat":39.62137132328378,"info":"直接查询获得"},{"name":"牛家牌镇","code":"120115123","level":4,"mergeName":"天津市,市辖区,宝坻区,牛家牌镇","lng":117.3045730105121,"lat":39.52803528421134,"info":"直接查询获得"},{"name":"尔王庄镇","code":"120115124","level":4,"mergeName":"天津市,市辖区,宝坻区,尔王庄镇","lng":117.37813936116683,"lat":39.40285066241293,"info":"直接查询获得"},{"name":"黄庄镇","code":"120115125","level":4,"mergeName":"天津市,市辖区,宝坻区,黄庄镇","lng":117.5316518874963,"lat":39.50203356992382,"info":"直接查询获得"},{"name":"口东镇","code":"120115126","level":4,"mergeName":"天津市,市辖区,宝坻区,口东镇","lng":117.3934806011069,"lat":39.647002829803824,"info":"直接查询获得"},{"name":"大白庄镇","code":"120115127","level":4,"mergeName":"天津市,市辖区,宝坻区,大白庄镇","lng":117.39591397239438,"lat":39.45493608177185,"info":"直接查询获得"},{"name":"宝坻经济开发区","code":"120115456","level":4,"mergeName":"天津市,市辖区,宝坻区,宝坻经济开发区","lng":117.31660069247685,"lat":39.723194482933174,"info":"直接查询获得"},{"name":"京津中关村科技城","code":"120115457","level":4,"mergeName":"天津市,市辖区,宝坻区,京津中关村科技城","lng":117.31660069247685,"lat":39.723194482933174,"info":"直接查询获得"},{"name":"里自沽农场","code":"120115500","level":4,"mergeName":"天津市,市辖区,宝坻区,里自沽农场","lng":117.35408051360857,"lat":39.49477801448984,"info":"直接查询获得"},{"name":"黄庄农场","code":"120115501","level":4,"mergeName":"天津市,市辖区,宝坻区,黄庄农场","lng":117.31660069247685,"lat":39.723194482933174,"info":"直接查询获得"},{"name":"大钟农场","code":"120115502","level":4,"mergeName":"天津市,市辖区,宝坻区,大钟农场","lng":117.31660069247685,"lat":39.723194482933174,"info":"直接查询获得"},{"name":"滨海新区","code":"120116","level":3,"mergeName":"天津市,市辖区,滨海新区","lng":117.71739882966088,"lat":39.00941577364663,"info":"直接查询获得"},{"name":"塘沽街道","code":"120116001","level":4,"mergeName":"天津市,市辖区,滨海新区,塘沽街道","lng":117.70279929902107,"lat":39.02373959832224,"info":"直接查询获得"},{"name":"杭州道街道","code":"120116005","level":4,"mergeName":"天津市,市辖区,滨海新区,杭州道街道","lng":117.61423718325082,"lat":38.89037712861296,"info":"直接查询获得"},{"name":"新河街道","code":"120116006","level":4,"mergeName":"天津市,市辖区,滨海新区,新河街道","lng":117.63896301456549,"lat":39.04466208116641,"info":"直接查询获得"},{"name":"大沽街道","code":"120116007","level":4,"mergeName":"天津市,市辖区,滨海新区,大沽街道","lng":117.67358757163376,"lat":38.991322742406005,"info":"直接查询获得"},{"name":"新北街道","code":"120116008","level":4,"mergeName":"天津市,市辖区,滨海新区,新北街道","lng":117.66803092324068,"lat":39.06087101641807,"info":"直接查询获得"},{"name":"北塘街道","code":"120116009","level":4,"mergeName":"天津市,市辖区,滨海新区,北塘街道","lng":117.71831653856988,"lat":39.10632880493473,"info":"直接查询获得"},{"name":"胡家园街道","code":"120116011","level":4,"mergeName":"天津市,市辖区,滨海新区,胡家园街道","lng":117.58845902116683,"lat":39.01797708905441,"info":"直接查询获得"},{"name":"新港街道","code":"120116012","level":4,"mergeName":"天津市,市辖区,滨海新区,新港街道","lng":117.71739882966088,"lat":39.00941577364663,"info":"直接查询获得"},{"name":"新村街道","code":"120116013","level":4,"mergeName":"天津市,市辖区,滨海新区,新村街道","lng":117.71739882966088,"lat":39.00941577364663,"info":"直接查询获得"},{"name":"天津经济技术开发区东区泰达街道","code":"120116014","level":4,"mergeName":"天津市,市辖区,滨海新区,天津经济技术开发区东区泰达街道","lng":117.70332947893306,"lat":39.0264396086254,"info":"直接查询获得"},{"name":"汉沽街道","code":"120116031","level":4,"mergeName":"天津市,市辖区,滨海新区,汉沽街道","lng":117.80850299821073,"lat":39.262364096876226,"info":"直接查询获得"},{"name":"寨上街道","code":"120116032","level":4,"mergeName":"天津市,市辖区,滨海新区,寨上街道","lng":117.83213795516156,"lat":39.25017909338876,"info":"直接查询获得"},{"name":"茶淀街道","code":"120116033","level":4,"mergeName":"天津市,市辖区,滨海新区,茶淀街道","lng":117.75451250146672,"lat":39.26480335538294,"info":"直接查询获得"},{"name":"大港街道","code":"120116051","level":4,"mergeName":"天津市,市辖区,滨海新区,大港街道","lng":117.45688864625805,"lat":38.834841128335015,"info":"直接查询获得"},{"name":"古林街道","code":"120116053","level":4,"mergeName":"天津市,市辖区,滨海新区,古林街道","lng":117.49243815706922,"lat":38.83831025085559,"info":"直接查询获得"},{"name":"海滨街道","code":"120116054","level":4,"mergeName":"天津市,市辖区,滨海新区,海滨街道","lng":117.39763665287086,"lat":38.6780138081378,"info":"直接查询获得"},{"name":"新城镇","code":"120116100","level":4,"mergeName":"天津市,市辖区,滨海新区,新城镇","lng":117.61902296783832,"lat":38.99417409465791,"info":"直接查询获得"},{"name":"杨家泊镇","code":"120116135","level":4,"mergeName":"天津市,市辖区,滨海新区,杨家泊镇","lng":117.91283004420633,"lat":39.30516107656758,"info":"直接查询获得"},{"name":"太平镇","code":"120116156","level":4,"mergeName":"天津市,市辖区,滨海新区,太平镇","lng":117.34300395751778,"lat":38.62383408888604,"info":"直接查询获得"},{"name":"小王庄镇","code":"120116157","level":4,"mergeName":"天津市,市辖区,滨海新区,小王庄镇","lng":117.16661448418952,"lat":38.757537733134605,"info":"直接查询获得"},{"name":"中塘镇","code":"120116158","level":4,"mergeName":"天津市,市辖区,滨海新区,中塘镇","lng":117.39209033499115,"lat":38.872629397916185,"info":"直接查询获得"},{"name":"天津经济技术开发区（其他片区）","code":"120116400","level":4,"mergeName":"天津市,市辖区,滨海新区,天津经济技术开发区（其他片区）","lng":117.71739882966088,"lat":39.00941577364663,"info":"直接查询获得"},{"name":"天津港保税区","code":"120116401","level":4,"mergeName":"天津市,市辖区,滨海新区,天津港保税区","lng":117.76549204056242,"lat":39.00410511087768,"info":"直接查询获得"},{"name":"天津滨海新区高新技术产业开发区","code":"120116402","level":4,"mergeName":"天津市,市辖区,滨海新区,天津滨海新区高新技术产业开发区","lng":117.70840364743673,"lat":39.08110856606096,"info":"直接查询获得"},{"name":"东疆保税港区","code":"120116403","level":4,"mergeName":"天津市,市辖区,滨海新区,东疆保税港区","lng":117.81819903839379,"lat":39.029220095028045,"info":"直接查询获得"},{"name":"中新天津生态城","code":"120116406","level":4,"mergeName":"天津市,市辖区,滨海新区,中新天津生态城","lng":117.80483297104972,"lat":39.165618117359685,"info":"直接查询获得"},{"name":"宁河区","code":"120117","level":3,"mergeName":"天津市,市辖区,宁河区","lng":117.83239334341803,"lat":39.33695643122726,"info":"直接查询获得"},{"name":"芦台街道","code":"120117001","level":4,"mergeName":"天津市,市辖区,宁河区,芦台街道","lng":117.83239334341803,"lat":39.33695643122726,"info":"直接查询获得"},{"name":"桥北街道","code":"120117002","level":4,"mergeName":"天津市,市辖区,宁河区,桥北街道","lng":117.83239334341803,"lat":39.33695643122726,"info":"直接查询获得"},{"name":"宁河镇","code":"120117102","level":4,"mergeName":"天津市,市辖区,宁河区,宁河镇","lng":117.72337860779663,"lat":39.496284013675634,"info":"直接查询获得"},{"name":"苗庄镇","code":"120117103","level":4,"mergeName":"天津市,市辖区,宁河区,苗庄镇","lng":117.80053170460684,"lat":39.43230270520167,"info":"直接查询获得"},{"name":"丰台镇","code":"120117104","level":4,"mergeName":"天津市,市辖区,宁河区,丰台镇","lng":117.76483699618456,"lat":39.55307313138344,"info":"直接查询获得"},{"name":"岳龙镇","code":"120117105","level":4,"mergeName":"天津市,市辖区,宁河区,岳龙镇","lng":117.88495881052137,"lat":39.55553836976999,"info":"直接查询获得"},{"name":"板桥镇","code":"120117106","level":4,"mergeName":"天津市,市辖区,宁河区,板桥镇","lng":117.81504580639265,"lat":39.49285516328921,"info":"直接查询获得"},{"name":"潘庄镇","code":"120117107","level":4,"mergeName":"天津市,市辖区,宁河区,潘庄镇","lng":117.44306896517384,"lat":39.337855401569335,"info":"直接查询获得"},{"name":"造甲城镇","code":"120117109","level":4,"mergeName":"天津市,市辖区,宁河区,造甲城镇","lng":117.47964368062286,"lat":39.267820170082764,"info":"直接查询获得"},{"name":"七里海镇","code":"120117110","level":4,"mergeName":"天津市,市辖区,宁河区,七里海镇","lng":117.6803227968559,"lat":39.31559197115703,"info":"直接查询获得"},{"name":"大北涧沽镇","code":"120117111","level":4,"mergeName":"天津市,市辖区,宁河区,大北涧沽镇","lng":117.7479034881687,"lat":39.34776645232214,"info":"直接查询获得"},{"name":"东棘坨镇","code":"120117112","level":4,"mergeName":"天津市,市辖区,宁河区,东棘坨镇","lng":117.56336548555946,"lat":39.42567418074139,"info":"直接查询获得"},{"name":"北淮淀镇","code":"120117113","level":4,"mergeName":"天津市,市辖区,宁河区,北淮淀镇","lng":117.58049087163221,"lat":39.253732042262804,"info":"直接查询获得"},{"name":"俵口镇","code":"120117114","level":4,"mergeName":"天津市,市辖区,宁河区,俵口镇","lng":117.59566304957701,"lat":39.32763666062225,"info":"直接查询获得"},{"name":"廉庄镇","code":"120117115","level":4,"mergeName":"天津市,市辖区,宁河区,廉庄镇","lng":117.70294096179998,"lat":39.42481609900967,"info":"直接查询获得"},{"name":"宁河区贸易开发区","code":"120117400","level":4,"mergeName":"天津市,市辖区,宁河区,宁河区贸易开发区","lng":117.82301647118268,"lat":39.35209501052533,"info":"直接查询获得"},{"name":"宁河区经济开发区","code":"120117401","level":4,"mergeName":"天津市,市辖区,宁河区,宁河区经济开发区","lng":117.83239334341803,"lat":39.33695643122726,"info":"直接查询获得"},{"name":"天津未来科技城天津经济技术开发区片区","code":"120117402","level":4,"mergeName":"天津市,市辖区,宁河区,天津未来科技城天津经济技术开发区片区","lng":117.83239334341803,"lat":39.33695643122726,"info":"直接查询获得"},{"name":"天津未来科技城滨海高新区片区","code":"120117403","level":4,"mergeName":"天津市,市辖区,宁河区,天津未来科技城滨海高新区片区","lng":117.83239334341803,"lat":39.33695643122726,"info":"直接查询获得"},{"name":"天津未来科技城宁河片区现代产业区组团","code":"120117451","level":4,"mergeName":"天津市,市辖区,宁河区,天津未来科技城宁河片区现代产业区组团","lng":117.4473135763865,"lat":39.2477189953284,"info":"直接查询获得"},{"name":"天津未来科技城宁河片区潘庄工业区组团","code":"120117452","level":4,"mergeName":"天津市,市辖区,宁河区,天津未来科技城宁河片区潘庄工业区组团","lng":117.42002485160438,"lat":39.30479989692935,"info":"直接查询获得"},{"name":"天津未来科技城宁河片区北淮淀组团","code":"120117453","level":4,"mergeName":"天津市,市辖区,宁河区,天津未来科技城宁河片区北淮淀组团","lng":117.83239334341803,"lat":39.33695643122726,"info":"直接查询获得"},{"name":"静海区","code":"120118","level":3,"mergeName":"天津市,市辖区,静海区","lng":116.98046860454797,"lat":38.95337068917225,"info":"直接查询获得"},{"name":"华康街道","code":"120118001","level":4,"mergeName":"天津市,市辖区,静海区,华康街道","lng":116.98046860454797,"lat":38.95337068917225,"info":"直接查询获得"},{"name":"静海镇","code":"120118100","level":4,"mergeName":"天津市,市辖区,静海区,静海镇","lng":116.98193580693741,"lat":38.9538915163576,"info":"直接查询获得"},{"name":"唐官屯镇","code":"120118101","level":4,"mergeName":"天津市,市辖区,静海区,唐官屯镇","lng":116.91654257937195,"lat":38.71404659344422,"info":"直接查询获得"},{"name":"独流镇","code":"120118102","level":4,"mergeName":"天津市,市辖区,静海区,独流镇","lng":116.89440871069102,"lat":39.03283178479835,"info":"直接查询获得"},{"name":"王口镇","code":"120118103","level":4,"mergeName":"天津市,市辖区,静海区,王口镇","lng":116.76409632551334,"lat":38.93979261356735,"info":"直接查询获得"},{"name":"台头镇","code":"120118104","level":4,"mergeName":"天津市,市辖区,静海区,台头镇","lng":116.79507730153477,"lat":39.027783934070754,"info":"直接查询获得"},{"name":"子牙镇","code":"120118105","level":4,"mergeName":"天津市,市辖区,静海区,子牙镇","lng":116.78146384085325,"lat":38.829327639666566,"info":"直接查询获得"},{"name":"陈官屯镇","code":"120118106","level":4,"mergeName":"天津市,市辖区,静海区,陈官屯镇","lng":116.91996503353441,"lat":38.82628612316125,"info":"直接查询获得"},{"name":"中旺镇","code":"120118107","level":4,"mergeName":"天津市,市辖区,静海区,中旺镇","lng":117.11363569683971,"lat":38.67155522707038,"info":"直接查询获得"},{"name":"大邱庄镇","code":"120118108","level":4,"mergeName":"天津市,市辖区,静海区,大邱庄镇","lng":117.07110143219671,"lat":38.838464682188906,"info":"直接查询获得"},{"name":"蔡公庄镇","code":"120118109","level":4,"mergeName":"天津市,市辖区,静海区,蔡公庄镇","lng":117.08853574553437,"lat":38.79502954151327,"info":"直接查询获得"},{"name":"梁头镇","code":"120118110","level":4,"mergeName":"天津市,市辖区,静海区,梁头镇","lng":116.86094645135941,"lat":38.941473875529205,"info":"直接查询获得"},{"name":"团泊镇","code":"120118111","level":4,"mergeName":"天津市,市辖区,静海区,团泊镇","lng":117.15779801266014,"lat":38.87673908305479,"info":"直接查询获得"},{"name":"双塘镇","code":"120118112","level":4,"mergeName":"天津市,市辖区,静海区,双塘镇","lng":116.91862521086628,"lat":38.8779886894933,"info":"直接查询获得"},{"name":"大丰堆镇","code":"120118113","level":4,"mergeName":"天津市,市辖区,静海区,大丰堆镇","lng":117.01328505228571,"lat":38.90258235604178,"info":"直接查询获得"},{"name":"沿庄镇","code":"120118114","level":4,"mergeName":"天津市,市辖区,静海区,沿庄镇","lng":116.7664818117273,"lat":38.79089644363949,"info":"直接查询获得"},{"name":"西翟庄镇","code":"120118115","level":4,"mergeName":"天津市,市辖区,静海区,西翟庄镇","lng":117.01862179548995,"lat":38.77151248730934,"info":"直接查询获得"},{"name":"良王庄乡","code":"120118200","level":4,"mergeName":"天津市,市辖区,静海区,良王庄乡","lng":116.98178650856164,"lat":39.031712706188706,"info":"直接查询获得"},{"name":"杨成庄乡","code":"120118201","level":4,"mergeName":"天津市,市辖区,静海区,杨成庄乡","lng":117.06659741730194,"lat":38.95578189021185,"info":"直接查询获得"},{"name":"天津静海经济开发区","code":"120118400","level":4,"mergeName":"天津市,市辖区,静海区,天津静海经济开发区","lng":116.98046860454797,"lat":38.95337068917225,"info":"直接查询获得"},{"name":"天津子牙循环经济产业区","code":"120118402","level":4,"mergeName":"天津市,市辖区,静海区,天津子牙循环经济产业区","lng":116.79340303972526,"lat":38.85126788774182,"info":"直接查询获得"},{"name":"团泊新城","code":"120118403","level":4,"mergeName":"天津市,市辖区,静海区,团泊新城","lng":117.15853503460222,"lat":38.895756097156145,"info":"直接查询获得"},{"name":"蓟州区","code":"120119","level":3,"mergeName":"天津市,市辖区,蓟州区","lng":117.41457869478904,"lat":40.051508786394855,"info":"直接查询获得"},{"name":"文昌街道","code":"120119001","level":4,"mergeName":"天津市,市辖区,蓟州区,文昌街道","lng":117.43424296172466,"lat":40.04736106471536,"info":"直接查询获得"},{"name":"渔阳镇","code":"120119100","level":4,"mergeName":"天津市,市辖区,蓟州区,渔阳镇","lng":117.41334199759346,"lat":40.040365048331665,"info":"直接查询获得"},{"name":"洇溜镇","code":"120119101","level":4,"mergeName":"天津市,市辖区,蓟州区,洇溜镇","lng":117.41231604287051,"lat":39.990698065386844,"info":"直接查询获得"},{"name":"官庄镇","code":"120119102","level":4,"mergeName":"天津市,市辖区,蓟州区,官庄镇","lng":117.31684449259227,"lat":40.06827140404341,"info":"直接查询获得"},{"name":"马伸桥镇","code":"120119103","level":4,"mergeName":"天津市,市辖区,蓟州区,马伸桥镇","lng":117.6108233249738,"lat":40.090801892044574,"info":"直接查询获得"},{"name":"下营镇","code":"120119104","level":4,"mergeName":"天津市,市辖区,蓟州区,下营镇","lng":117.4412997803194,"lat":40.197763673510906,"info":"直接查询获得"},{"name":"邦均镇","code":"120119105","level":4,"mergeName":"天津市,市辖区,蓟州区,邦均镇","lng":117.30656123009734,"lat":39.99643448011251,"info":"直接查询获得"},{"name":"别山镇","code":"120119106","level":4,"mergeName":"天津市,市辖区,蓟州区,别山镇","lng":117.5014391782792,"lat":39.966178871324225,"info":"直接查询获得"},{"name":"尤古庄镇","code":"120119108","level":4,"mergeName":"天津市,市辖区,蓟州区,尤古庄镇","lng":117.25837414627,"lat":39.91554188875397,"info":"直接查询获得"},{"name":"上仓镇","code":"120119109","level":4,"mergeName":"天津市,市辖区,蓟州区,上仓镇","lng":117.4088256768115,"lat":39.9119681218584,"info":"直接查询获得"},{"name":"下仓镇","code":"120119111","level":4,"mergeName":"天津市,市辖区,蓟州区,下仓镇","lng":117.43045804128892,"lat":39.79497909713224,"info":"直接查询获得"},{"name":"罗庄子镇","code":"120119112","level":4,"mergeName":"天津市,市辖区,蓟州区,罗庄子镇","lng":117.42630122237205,"lat":40.14482813056895,"info":"直接查询获得"},{"name":"白涧镇","code":"120119113","level":4,"mergeName":"天津市,市辖区,蓟州区,白涧镇","lng":117.22763905533105,"lat":40.026489097883086,"info":"直接查询获得"},{"name":"侯家营镇","code":"120119115","level":4,"mergeName":"天津市,市辖区,蓟州区,侯家营镇","lng":117.26166221392818,"lat":39.86232971474898,"info":"直接查询获得"},{"name":"桑梓镇","code":"120119116","level":4,"mergeName":"天津市,市辖区,蓟州区,桑梓镇","lng":117.17847867455146,"lat":39.91562766625763,"info":"直接查询获得"},{"name":"东施古镇","code":"120119117","level":4,"mergeName":"天津市,市辖区,蓟州区,东施古镇","lng":117.33579649308902,"lat":39.89291083154041,"info":"直接查询获得"},{"name":"下窝头镇","code":"120119118","level":4,"mergeName":"天津市,市辖区,蓟州区,下窝头镇","lng":117.41250648363864,"lat":39.86982866691195,"info":"直接查询获得"},{"name":"杨津庄镇","code":"120119119","level":4,"mergeName":"天津市,市辖区,蓟州区,杨津庄镇","lng":117.43925415901208,"lat":39.873548692310955,"info":"直接查询获得"},{"name":"出头岭镇","code":"120119120","level":4,"mergeName":"天津市,市辖区,蓟州区,出头岭镇","lng":117.68359244925114,"lat":40.08101572687067,"info":"直接查询获得"},{"name":"西龙虎峪镇","code":"120119121","level":4,"mergeName":"天津市,市辖区,蓟州区,西龙虎峪镇","lng":117.7293246437808,"lat":40.00853524959933,"info":"直接查询获得"},{"name":"穿芳峪镇","code":"120119122","level":4,"mergeName":"天津市,市辖区,蓟州区,穿芳峪镇","lng":117.54921627547178,"lat":40.10432092368552,"info":"直接查询获得"},{"name":"东二营镇","code":"120119123","level":4,"mergeName":"天津市,市辖区,蓟州区,东二营镇","lng":117.299711201431,"lat":39.9656267767376,"info":"直接查询获得"},{"name":"许家台镇","code":"120119124","level":4,"mergeName":"天津市,市辖区,蓟州区,许家台镇","lng":117.2775603350132,"lat":40.04079991251474,"info":"直接查询获得"},{"name":"礼明庄镇","code":"120119125","level":4,"mergeName":"天津市,市辖区,蓟州区,礼明庄镇","lng":117.44819032256424,"lat":39.96321408379717,"info":"直接查询获得"},{"name":"东赵各庄镇","code":"120119126","level":4,"mergeName":"天津市,市辖区,蓟州区,东赵各庄镇","lng":117.35968971287397,"lat":39.969632764847596,"info":"直接查询获得"},{"name":"州河湾镇","code":"120119127","level":4,"mergeName":"天津市,市辖区,蓟州区,州河湾镇","lng":117.41457869478904,"lat":40.051508786394855,"info":"直接查询获得"},{"name":"孙各庄乡","code":"120119203","level":4,"mergeName":"天津市,市辖区,蓟州区,孙各庄乡","lng":117.41457869478904,"lat":40.051508786394855,"info":"直接查询获得"},{"name":"天津市蓟州区京津州河科技产业园管理委员会","code":"120119401","level":4,"mergeName":"天津市,市辖区,蓟州区,天津市蓟州区京津州河科技产业园管理委员会","lng":117.44605496053646,"lat":39.97918010114088,"info":"直接查询获得"}]